reliabilipy/__init__.py
reliabilipy/_reliabili.py
tests/__init__.py
tests/test_reliabili.py
reliabiliPy-0.0.35.dist-info/LICENSE
reliabiliPy-0.0.35.dist-info/METADATA
reliabiliPy-0.0.35.dist-info/WHEEL
reliabiliPy-0.0.35.dist-info/top_level.txt
reliabiliPy-0.0.35.dist-info/RECORD
