Metadata-Version: 2.1
Name: reliabiliPy
Version: 0.0.35
Summary: Simple implementation in Python of the reliability: Omega Total,Omega Hierarchical, Omega Hierarchical Total, Cronbach's Alpha and more.
Home-page: https://github.com/rafaelvalero/reliabiliPy
Author: Rafael Valero-Fernandez
Author-email: rafael.valero.fernandez@gmail.com
License: UNKNOWN
Platform: UNKNOWN
Classifier: Programming Language :: Python :: 3
Classifier: License :: OSI Approved :: MIT License
Classifier: Operating System :: OS Independent
Requires-Python: >=3.6
License-File: LICENSE
Requires-Dist: factor-analyzer (>=0.4.0)
